{
    "domain": "Browser",
    "description": "The Browser domain defines methods and events for browser managing.",
    "types": [
        {
            "id": "BrowserContextID",
            "experimental": true,
            "type": "string"
        },
        {
            "id": "WindowID",
            "experimental": true,
            "type": "integer"
        },
        {
            "id": "WindowState",
            "description": "The state of the browser window.",
            "experimental": true,
            "type": "string",
            "enum": [
                "normal",
                "minimized",
                "maximized",
                "fullscreen"
            ]
        },
        {
            "id": "Bounds",
            "description": "Browser window bounds information",
            "experimental": true,
            "type": "object",
            "properties": [
                {
                    "name": "left",
                    "description": "The offset from the left edge of the screen to the window in pixels.",
                    "optional": true,
                    "type": "integer"
                },
                {
                    "name": "top",
                    "description": "The offset from the top edge of the screen to the window in pixels.",
                    "optional": true,
                    "type": "integer"
                },
                {
                    "name": "width",
                    "description": "The window width in pixels.",
                    "optional": true,
                    "type": "integer"
                },
                {
                    "name": "height",
                    "description": "The window height in pixels.",
                    "optional": true,
                    "type": "integer"
                },
                {
                    "name": "windowState",
                    "description": "The window state. Default to normal.",
                    "optional": true,
                    "$ref": "WindowState"
                }
            ]
        },
        {
            "id": "PermissionType",
            "experimental": true,
            "type": "string",
            "enum": [
                "ar",
                "audioCapture",
                "automaticFullscreen",
                "backgroundFetch",
                "backgroundSync",
                "cameraPanTiltZoom",
                "capturedSurfaceControl",
                "clipboardReadWrite",
                "clipboardSanitizedWrite",
                "displayCapture",
                "durableStorage",
                "geolocation",
                "handTracking",
                "idleDetection",
                "keyboardLock",
                "localFonts",
                "localNetwork",
                "localNetworkAccess",
                "loopbackNetwork",
                "midi",
                "midiSysex",
                "nfc",
                "notifications",
                "paymentHandler",
                "periodicBackgroundSync",
                "pointerLock",
                "protectedMediaIdentifier",
                "sensors",
                "smartCard",
                "speakerSelection",
                "storageAccess",
                "topLevelStorageAccess",
                "videoCapture",
                "vr",
                "wakeLockScreen",
                "wakeLockSystem",
                "webAppInstallation",
                "webPrinting",
                "windowManagement"
            ]
        },
        {
            "id": "PermissionSetting",
            "experimental": true,
            "type": "string",
            "enum": [
                "granted",
                "denied",
                "prompt"
            ]
        },
        {
            "id": "PermissionDescriptor",
            "description": "Definition of PermissionDescriptor defined in the Permissions API:\nhttps://w3c.github.io/permissions/#dom-permissiondescriptor.",
            "experimental": true,
            "type": "object",
            "properties": [
                {
                    "name": "name",
                    "description": "Name of permission.\nSee https://cs.chromium.org/chromium/src/third_party/blink/renderer/modules/permissions/permission_descriptor.idl for valid permission names.",
                    "type": "string"
                },
                {
                    "name": "sysex",
                    "description": "For \"midi\" permission, may also specify sysex control.",
                    "optional": true,
                    "type": "boolean"
                },
                {
                    "name": "userVisibleOnly",
                    "description": "For \"push\" permission, may specify userVisibleOnly.\nNote that userVisibleOnly = true is the only currently supported type.",
                    "optional": true,
                    "type": "boolean"
                },
                {
                    "name": "allowWithoutSanitization",
                    "description": "For \"clipboard\" permission, may specify allowWithoutSanitization.",
                    "optional": true,
                    "type": "boolean"
                },
                {
                    "name": "allowWithoutGesture",
                    "description": "For \"fullscreen\" permission, must specify allowWithoutGesture:true.",
                    "optional": true,
                    "type": "boolean"
                },
                {
                    "name": "panTiltZoom",
                    "description": "For \"camera\" permission, may specify panTiltZoom.",
                    "optional": true,
                    "type": "boolean"
                }
            ]
        },
        {
            "id": "BrowserCommandId",
            "description": "Browser command ids used by executeBrowserCommand.",
            "experimental": true,
            "type": "string",
            "enum": [
                "openTabSearch",
                "closeTabSearch",
                "openGlic"
            ]
        },
        {
            "id": "Bucket",
            "description": "Chrome histogram bucket.",
            "experimental": true,
            "type": "object",
            "properties": [
                {
                    "name": "low",
                    "description": "Minimum value (inclusive).",
                    "type": "integer"
                },
                {
                    "name": "high",
                    "description": "Maximum value (exclusive).",
                    "type": "integer"
                },
                {
                    "name": "count",
                    "description": "Number of samples.",
                    "type": "integer"
                }
            ]
        },
        {
            "id": "Histogram",
            "description": "Chrome histogram.",
            "experimental": true,
            "type": "object",
            "properties": [
                {
                    "name": "name",
                    "description": "Name.",
                    "type": "string"
                },
                {
                    "name": "sum",
                    "description": "Sum of sample values.",
                    "type": "integer"
                },
                {
                    "name": "count",
                    "description": "Total number of samples.",
                    "type": "integer"
                },
                {
                    "name": "buckets",
                    "description": "Buckets.",
                    "type": "array",
                    "items": {
                        "$ref": "Bucket"
                    }
                }
            ]
        },
        {
            "id": "PrivacySandboxAPI",
            "experimental": true,
            "type": "string",
            "enum": [
                "BiddingAndAuctionServices",
                "TrustedKeyValue"
            ]
        }
    ],
    "commands": [
        {
            "name": "setPermission",
            "description": "Set permission settings for given embedding and embedded origins.",
            "experimental": true,
            "parameters": [
                {
                    "name": "permission",
                    "description": "Descriptor of permission to override.",
                    "$ref": "PermissionDescriptor"
                },
                {
                    "name": "setting",
                    "description": "Setting of the permission.",
                    "$ref": "PermissionSetting"
                },
                {
                    "name": "origin",
                    "description": "Embedding origin the permission applies to, all origins if not specified.",
                    "optional": true,
                    "type": "string"
                },
                {
                    "name": "embeddedOrigin",
                    "description": "Embedded origin the permission applies to. It is ignored unless the embedding origin is\npresent and valid. If the embedding origin is provided but the embedded origin isn't, the\nembedding origin is used as the embedded origin.",
                    "optional": true,
                    "type": "string"
                },
                {
                    "name": "browserContextId",
                    "description": "Context to override. When omitted, default browser context is used.",
                    "optional": true,
                    "$ref": "BrowserContextID"
                }
            ]
        },
        {
            "name": "grantPermissions",
            "description": "Grant specific permissions to the given origin and reject all others. Deprecated. Use\nsetPermission instead.",
            "experimental": true,
            "deprecated": true,
            "parameters": [
                {
                    "name": "permissions",
                    "type": "array",
                    "items": {
                        "$ref": "PermissionType"
                    }
                },
                {
                    "name": "origin",
                    "description": "Origin the permission applies to, all origins if not specified.",
                    "optional": true,
                    "type": "string"
                },
                {
                    "name": "browserContextId",
                    "description": "BrowserContext to override permissions. When omitted, default browser context is used.",
                    "optional": true,
                    "$ref": "BrowserContextID"
                }
            ]
        },
        {
            "name": "resetPermissions",
            "description": "Reset all permission management for all origins.",
            "parameters": [
                {
                    "name": "browserContextId",
                    "description": "BrowserContext to reset permissions. When omitted, default browser context is used.",
                    "optional": true,
                    "$ref": "BrowserContextID"
                }
            ]
        },
        {
            "name": "setDownloadBehavior",
            "description": "Set the behavior when downloading a file.",
            "experimental": true,
            "parameters": [
                {
                    "name": "behavior",
                    "description": "Whether to allow all or deny all download requests, or use default Chrome behavior if\navailable (otherwise deny). |allowAndName| allows download and names files according to\ntheir download guids.",
                    "type": "string",
                    "enum": [
                        "deny",
                        "allow",
                        "allowAndName",
                        "default"
                    ]
                },
                {
                    "name": "browserContextId",
                    "description": "BrowserContext to set download behavior. When omitted, default browser context is used.",
                    "optional": true,
                    "$ref": "BrowserContextID"
                },
                {
                    "name": "downloadPath",
                    "description": "The default path to save downloaded files to. This is required if behavior is set to 'allow'\nor 'allowAndName'.",
                    "optional": true,
                    "type": "string"
                },
                {
                    "name": "eventsEnabled",
                    "description": "Whether to emit download events (defaults to false).",
                    "optional": true,
                    "type": "boolean"
                }
            ]
        },
        {
            "name": "cancelDownload",
            "description": "Cancel a download if in progress",
            "experimental": true,
            "parameters": [
                {
                    "name": "guid",
                    "description": "Global unique identifier of the download.",
                    "type": "string"
                },
                {
                    "name": "browserContextId",
                    "description": "BrowserContext to perform the action in. When omitted, default browser context is used.",
                    "optional": true,
                    "$ref": "BrowserContextID"
                }
            ]
        },
        {
            "name": "close",
            "description": "Close browser gracefully."
        },
        {
            "name": "crash",
            "description": "Crashes browser on the main thread.",
            "experimental": true
        },
        {
            "name": "crashGpuProcess",
            "description": "Crashes GPU process.",
            "experimental": true
        },
        {
            "name": "getVersion",
            "description": "Returns version information.",
            "returns": [
                {
                    "name": "protocolVersion",
                    "description": "Protocol version.",
                    "type": "string"
                },
                {
                    "name": "product",
                    "description": "Product name.",
                    "type": "string"
                },
                {
                    "name": "revision",
                    "description": "Product revision.",
                    "type": "string"
                },
                {
                    "name": "userAgent",
                    "description": "User-Agent.",
                    "type": "string"
                },
                {
                    "name": "jsVersion",
                    "description": "V8 version.",
                    "type": "string"
                }
            ]
        },
        {
            "name": "getBrowserCommandLine",
            "description": "Returns the command line switches for the browser process if, and only if\n--enable-automation is on the commandline.",
            "experimental": true,
            "returns": [
                {
                    "name": "arguments",
                    "description": "Commandline parameters",
                    "type": "array",
                    "items": {
                        "type": "string"
                    }
                }
            ]
        },
        {
            "name": "getHistograms",
            "description": "Get Chrome histograms.",
            "experimental": true,
            "parameters": [
                {
                    "name": "query",
                    "description": "Requested substring in name. Only histograms which have query as a\nsubstring in their name are extracted. An empty or absent query returns\nall histograms.",
                    "optional": true,
                    "type": "string"
                },
                {
                    "name": "delta",
                    "description": "If true, retrieve delta since last delta call.",
                    "optional": true,
                    "type": "boolean"
                }
            ],
            "returns": [
                {
                    "name": "histograms",
                    "description": "Histograms.",
                    "type": "array",
                    "items": {
                        "$ref": "Histogram"
                    }
                }
            ]
        },
        {
            "name": "getHistogram",
            "description": "Get a Chrome histogram by name.",
            "experimental": true,
            "parameters": [
                {
                    "name": "name",
                    "description": "Requested histogram name.",
                    "type": "string"
                },
                {
                    "name": "delta",
                    "description": "If true, retrieve delta since last delta call.",
                    "optional": true,
                    "type": "boolean"
                }
            ],
            "returns": [
                {
                    "name": "histogram",
                    "description": "Histogram.",
                    "$ref": "Histogram"
                }
            ]
        },
        {
            "name": "getWindowBounds",
            "description": "Get position and size of the browser window.",
            "experimental": true,
            "parameters": [
                {
                    "name": "windowId",
                    "description": "Browser window id.",
                    "$ref": "WindowID"
                }
            ],
            "returns": [
                {
                    "name": "bounds",
                    "description": "Bounds information of the window. When window state is 'minimized', the restored window\nposition and size are returned.",
                    "$ref": "Bounds"
                }
            ]
        },
        {
            "name": "getWindowForTarget",
            "description": "Get the browser window that contains the devtools target.",
            "experimental": true,
            "parameters": [
                {
                    "name": "targetId",
                    "description": "Devtools agent host id. If called as a part of the session, associated targetId is used.",
                    "optional": true,
                    "$ref": "Target.TargetID"
                }
            ],
            "returns": [
                {
                    "name": "windowId",
                    "description": "Browser window id.",
                    "$ref": "WindowID"
                },
                {
                    "name": "bounds",
                    "description": "Bounds information of the window. When window state is 'minimized', the restored window\nposition and size are returned.",
                    "$ref": "Bounds"
                }
            ]
        },
        {
            "name": "setWindowBounds",
            "description": "Set position and/or size of the browser window.",
            "experimental": true,
            "parameters": [
                {
                    "name": "windowId",
                    "description": "Browser window id.",
                    "$ref": "WindowID"
                },
                {
                    "name": "bounds",
                    "description": "New window bounds. The 'minimized', 'maximized' and 'fullscreen' states cannot be combined\nwith 'left', 'top', 'width' or 'height'. Leaves unspecified fields unchanged.",
                    "$ref": "Bounds"
                }
            ]
        },
        {
            "name": "setContentsSize",
            "description": "Set size of the browser contents resizing browser window as necessary.",
            "experimental": true,
            "parameters": [
                {
                    "name": "windowId",
                    "description": "Browser window id.",
                    "$ref": "WindowID"
                },
                {
                    "name": "width",
                    "description": "The window contents width in DIP. Assumes current width if omitted.\nMust be specified if 'height' is omitted.",
                    "optional": true,
                    "type": "integer"
                },
                {
                    "name": "height",
                    "description": "The window contents height in DIP. Assumes current height if omitted.\nMust be specified if 'width' is omitted.",
                    "optional": true,
                    "type": "integer"
                }
            ]
        },
        {
            "name": "setDockTile",
            "description": "Set dock tile details, platform-specific.",
            "experimental": true,
            "parameters": [
                {
                    "name": "badgeLabel",
                    "optional": true,
                    "type": "string"
                },
                {
                    "name": "image",
                    "description": "Png encoded image. (Encoded as a base64 string when passed over JSON)",
                    "optional": true,
                    "type": "string"
                }
            ]
        },
        {
            "name": "executeBrowserCommand",
            "description": "Invoke custom browser commands used by telemetry.",
            "experimental": true,
            "parameters": [
                {
                    "name": "commandId",
                    "$ref": "BrowserCommandId"
                }
            ]
        },
        {
            "name": "addPrivacySandboxEnrollmentOverride",
            "description": "Allows a site to use privacy sandbox features that require enrollment\nwithout the site actually being enrolled. Only supported on page targets.",
            "parameters": [
                {
                    "name": "url",
                    "type": "string"
                }
            ]
        },
        {
            "name": "addPrivacySandboxCoordinatorKeyConfig",
            "description": "Configures encryption keys used with a given privacy sandbox API to talk\nto a trusted coordinator.  Since this is intended for test automation only,\ncoordinatorOrigin must be a .test domain. No existing coordinator\nconfiguration for the origin may exist.",
            "parameters": [
                {
                    "name": "api",
                    "$ref": "PrivacySandboxAPI"
                },
                {
                    "name": "coordinatorOrigin",
                    "type": "string"
                },
                {
                    "name": "keyConfig",
                    "type": "string"
                },
                {
                    "name": "browserContextId",
                    "description": "BrowserContext to perform the action in. When omitted, default browser\ncontext is used.",
                    "optional": true,
                    "$ref": "BrowserContextID"
                }
            ]
        }
    ],
    "events": [
        {
            "name": "downloadWillBegin",
            "description": "Fired when page is about to start a download.",
            "experimental": true,
            "parameters": [
                {
                    "name": "frameId",
                    "description": "Id of the frame that caused the download to begin.",
                    "$ref": "Page.FrameId"
                },
                {
                    "name": "guid",
                    "description": "Global unique identifier of the download.",
                    "type": "string"
                },
                {
                    "name": "url",
                    "description": "URL of the resource being downloaded.",
                    "type": "string"
                },
                {
                    "name": "suggestedFilename",
                    "description": "Suggested file name of the resource (the actual name of the file saved on disk may differ).",
                    "type": "string"
                }
            ]
        },
        {
            "name": "downloadProgress",
            "description": "Fired when download makes progress. Last call has |done| == true.",
            "experimental": true,
            "parameters": [
                {
                    "name": "guid",
                    "description": "Global unique identifier of the download.",
                    "type": "string"
                },
                {
                    "name": "totalBytes",
                    "description": "Total expected bytes to download.",
                    "type": "number"
                },
                {
                    "name": "receivedBytes",
                    "description": "Total bytes received.",
                    "type": "number"
                },
                {
                    "name": "state",
                    "description": "Download status.",
                    "type": "string",
                    "enum": [
                        "inProgress",
                        "completed",
                        "canceled"
                    ]
                },
                {
                    "name": "filePath",
                    "description": "If download is \"completed\", provides the path of the downloaded file.\nDepending on the platform, it is not guaranteed to be set, nor the file\nis guaranteed to exist.",
                    "experimental": true,
                    "optional": true,
                    "type": "string"
                }
            ]
        }
    ]
}